server.py
tushare_mcp_server-0.1.4.dist-info/licenses/LICENSE
tushare_mcp_server-0.1.4.dist-info/METADATA
tushare_mcp_server-0.1.4.dist-info/WHEEL
tushare_mcp_server-0.1.4.dist-info/entry_points.txt
tushare_mcp_server-0.1.4.dist-info/top_level.txt
tushare_mcp_server-0.1.4.dist-info/RECORD
