Metadata-Version: 2.4
Name: tushare-mcp-server
Version: 0.1.4
Summary: A Model Context Protocol (MCP) server for Tushare, providing Chinese financial market data.
Author: Michael Feng
License: GPL-3.0
Classifier: Programming Language :: Python :: 3
Classifier: License :: OSI Approved :: GNU General Public License v3 (GPLv3)
Classifier: Operating System :: OS Independent
Requires-Python: >=3.8
License-File: LICENSE
Requires-Dist: mcp>=1.0.0
Requires-Dist: tushare>=1.4.0
Requires-Dist: pandas>=2.0.0
Requires-Dist: numpy>=1.24.0
Requires-Dist: requests>=2.31.0
Requires-Dist: python-dotenv>=1.0.0
Requires-Dist: pydantic>=2.0.0
Requires-Dist: aiofiles>=23.0.0
Dynamic: license-file
